pybacmman/__init__.py
pybacmman/dataset/__init__.py
pybacmman/dataset/dataset.py
pybacmman/evaluation/__init__.py
pybacmman/evaluation/run_tasks.py
pybacmman/pandas/__init__.py
pybacmman/pandas/curve_utils.py
pybacmman/pandas/indices_utils.py
pybacmman/pandas/pandas_utils.py
pybacmman/pandas/track_utils.py
pybacmman/selections/__init__.py
pybacmman/selections/selections.py
pybacmman-0.6.5.dist-info/licenses/LICENSE
pybacmman-0.6.5.dist-info/METADATA
pybacmman-0.6.5.dist-info/WHEEL
pybacmman-0.6.5.dist-info/top_level.txt
pybacmman-0.6.5.dist-info/RECORD
