Metadata-Version: 2.4
Name: PyBacmman
Version: 0.6.5
Summary: Utilities for analysis of data generated from bacmman software
Home-page: https://github.com/jeanollion/PyBacmman.git
Download-URL: https://github.com/jeanollion/PyBacmman/archive/v0.6.4.tar.gz
Author: Jean Ollion
Author-email: jean.ollion@polytechnique.org
Keywords: bacmman,pandas,data analysis
Classifier: Development Status :: 4 - Beta
Classifier: Intended Audience :: Science/Research
Classifier: Programming Language :: Python :: 3
Classifier: License :: OSI Approved :: GNU General Public License v3 or later (GPLv3+)
Classifier: Operating System :: OS Independent
Requires-Python: >=3
License-File: LICENSE
Requires-Dist: py4j
Requires-Dist: pandas
Dynamic: author
Dynamic: author-email
Dynamic: classifier
Dynamic: description
Dynamic: description-content-type
Dynamic: download-url
Dynamic: home-page
Dynamic: keywords
Dynamic: license-file
Dynamic: requires-dist
Dynamic: requires-python
Dynamic: summary
